{"nodes": [{"id": "nfr_checklist_md", "label": "NFR Checklist", "file_type": "document", "source_file": ".agents/skills/architecture-designer/references/nfr-checklist.md", "source_location": null, "source_url": null, "captured_at": null, "author": null, "contributor": null}], "edges": [{"source": "nfr_checklist_md", "target": "improve_codebase_architecture_skill", "relation": "provides_checklist", "confidence": "INFERRED", "confidence_score": 0.7, "source_file": ".agents/skills/architecture-designer/references/nfr-checklist.md", "source_location": null, "weight": 0.7}], "hyperedges": []}