{"nodes": [{"id": "decisionlog_js", "label": "decisionLog.js", "file_type": "code", "source_file": "frontend/src/strategy/decisionLog.js", "source_location": null, "source_url": null, "captured_at": null, "author": null, "contributor": null}, {"id": "declog_accsummary", "label": "ACC Summary (accSummary)", "file_type": "code", "source_file": "frontend/src/strategy/decisionLog.js", "source_location": null, "source_url": null, "captured_at": null, "author": null, "contributor": null}, {"id": "declog_builddecisionrecord", "label": "Build Decision Record (buildDecisionRecord)", "file_type": "code", "source_file": "frontend/src/strategy/decisionLog.js", "source_location": null, "source_url": null, "captured_at": null, "author": null, "contributor": null}, {"id": "declog_recorddecision", "label": "Record Decision (recordDecision)", "file_type": "code", "source_file": "frontend/src/strategy/decisionLog.js", "source_location": null, "source_url": null, "captured_at": null, "author": null, "contributor": null}], "edges": [{"source": "decisionlog_js", "target": "declog_accsummary", "relation": "defines", "confidence": "EXTRACTED", "confidence_score": 1.0, "source_file": "frontend/src/strategy/decisionLog.js", "source_location": null, "weight": 1.0}, {"source": "decisionlog_js", "target": "declog_builddecisionrecord", "relation": "defines", "confidence": "EXTRACTED", "confidence_score": 1.0, "source_file": "frontend/src/strategy/decisionLog.js", "source_location": null, "weight": 1.0}, {"source": "decisionlog_js", "target": "declog_recorddecision", "relation": "defines", "confidence": "EXTRACTED", "confidence_score": 1.0, "source_file": "frontend/src/strategy/decisionLog.js", "source_location": null, "weight": 1.0}, {"source": "declog_builddecisionrecord", "target": "declog_accsummary", "relation": "calls", "confidence": "EXTRACTED", "confidence_score": 1.0, "source_file": "frontend/src/strategy/decisionLog.js", "source_location": null, "weight": 1.0}, {"source": "declog_accsummary", "target": "council_js", "relation": "conceptually_related_to", "confidence": "INFERRED", "confidence_score": 0.8, "source_file": "frontend/src/strategy/decisionLog.js", "source_location": null, "weight": 1.0}], "hyperedges": []}